Metadata-Version: 2.1
Name: listdlls
Version: 0.0.5
Summary: A small example package
Home-page: https://github.com/Pixelsuft/listdlls
Author: Pixelsuft
License: MIT
Keywords: listdlls
Platform: UNKNOWN
Classifier: Programming Language :: Python :: 3
Classifier: License :: OSI Approved :: MIT License
Classifier: Operating System :: Microsoft :: Windows :: Windows 10
Requires-Python: >=3.5
